anansi_toolkit/__init__.py
anansi_toolkit/marketdata/__init__.py
anansi_toolkit/marketdata/data_brokers.py
anansi_toolkit/marketdata/handlers.py
anansi_toolkit/marketdata/indicators.py
anansi_toolkit/settings.py
anansi_toolkit/share/__init__.py
anansi_toolkit/share/db_handlers.py
anansi_toolkit/share/tools.py
anansi_toolkit/tradingbot/__init__.py
anansi_toolkit/tradingbot/classifiers.py
anansi_toolkit/tradingbot/models.py
anansi_toolkit/tradingbot/order_handler.py
anansi_toolkit/tradingbot/stop_handlers.py
anansi_toolkit/tradingbot/trade_brokers.py
anansi_toolkit/tradingbot/traders.py
anansi_toolkit/tradingbot/views.py
anansi_toolkit-0.1.0.dist-info/LICENSE
anansi_toolkit-0.1.0.dist-info/WHEEL
anansi_toolkit-0.1.0.dist-info/METADATA
anansi_toolkit-0.1.0.dist-info/RECORD
